habit_tracker/__init__.py
habit_tracker/habit_tracker.py
habit_tracker/main.py
habit_tracker-0.1.0.dist-info/METADATA
habit_tracker-0.1.0.dist-info/WHEEL
habit_tracker-0.1.0.dist-info/entry_points.txt
habit_tracker-0.1.0.dist-info/top_level.txt
habit_tracker-0.1.0.dist-info/RECORD
